abot/__init__.py
abot/bot.py
abot/cli.py
abot/dubtrack.py
abot/slack.py
abot/util.py
abot-0.0.1a1.dev19.dist-info/METADATA
abot-0.0.1a1.dev19.dist-info/RECORD
abot-0.0.1a1.dev19.dist-info/WHEEL
abot-0.0.1a1.dev19.dist-info/top_level.txt
