Metadata-Version: 2.1
Name: abot
Version: 0.0.1a1.dev19
Summary: Bot creation library
Home-page: https://github.com/txomon/abot
Author: Javier Domingo Cansino
Author-email: javierdo1@gmail.com
License: MIT
Keywords: slack,dubtrack,bot,async,asyncio
Platform: UNKNOWN
Classifier: Development Status :: 1 - Planning
Classifier: Intended Audience :: Developers
Classifier: Topic :: Software Development :: Libraries
Classifier: License :: OSI Approved :: MIT License
Classifier: Programming Language :: Python :: 3.6
Requires-Python: >=3.6
Requires-Dist: aiohttp
Requires-Dist: click
